<?xml version="1.0" encoding="utf-8" ?>
<dwsync>
<file name="app-calendar.css" server="ftp.appcasoclinico.com.br//public_html/" local="133647598795478868" remote="133722664200000000" Dst="0" />
<file name="app-chat-list.css" server="ftp.appcasoclinico.com.br//public_html/" local="133647598735617922" remote="133722664200000000" Dst="0" />
<file name="app-calendar.min.css" server="ftp.appcasoclinico.com.br//public_html/" local="133647598770908174" remote="133722664200000000" Dst="0" />
<file name="app-chat-list.min.css" server="ftp.appcasoclinico.com.br//public_html/" local="133647598937246945" remote="133722664200000000" Dst="0" />
<file name="app-chat.css" server="ftp.appcasoclinico.com.br//public_html/" local="133647598872908688" remote="133722664200000000" Dst="0" />
<file name="app-chat.min.css" server="ftp.appcasoclinico.com.br//public_html/" local="133647598729628821" remote="133722664200000000" Dst="0" />
<file name="app-ecommerce-details.css" server="ftp.appcasoclinico.com.br//public_html/" local="133647598904277169" remote="133722664200000000" Dst="0" />
<file name="app-ecommerce-details.min.css" server="ftp.appcasoclinico.com.br//public_html/" local="133647598676196360" remote="133722664200000000" Dst="0" />
<file name="app-ecommerce.css" server="ftp.appcasoclinico.com.br//public_html/" local="133647598721565342" remote="133722664200000000" Dst="0" />
<file name="app-ecommerce.min.css" server="ftp.appcasoclinico.com.br//public_html/" local="133647598810221262" remote="133722664200000000" Dst="0" />
<file name="app-email.css" server="ftp.appcasoclinico.com.br//public_html/" local="133647598853378390" remote="133722664200000000" Dst="0" />
<file name="app-email.min.css" server="ftp.appcasoclinico.com.br//public_html/" local="133647598892058773" remote="133722664200000000" Dst="0" />
<file name="app-file-manager.css" server="ftp.appcasoclinico.com.br//public_html/" local="133647598715604120" remote="133722664200000000" Dst="0" />
<file name="app-file-manager.min.css" server="ftp.appcasoclinico.com.br//public_html/" local="133647598922354072" remote="133722664200000000" Dst="0" />
<file name="app-invoice-list.css" server="ftp.appcasoclinico.com.br//public_html/" local="133647598688227410" remote="133722664200000000" Dst="0" />
<file name="app-invoice-print.css" server="ftp.appcasoclinico.com.br//public_html/" local="133647598945411261" remote="133722664200000000" Dst="0" />
<file name="app-invoice-list.min.css" server="ftp.appcasoclinico.com.br//public_html/" local="133647598703571108" remote="133722664200000000" Dst="0" />
<file name="app-invoice-print.min.css" server="ftp.appcasoclinico.com.br//public_html/" local="133647598757881162" remote="133722664200000000" Dst="0" />
<file name="app-invoice.css" server="ftp.appcasoclinico.com.br//public_html/" local="133647598910107929" remote="133722664200000000" Dst="0" />
<file name="app-invoice.min.css" server="ftp.appcasoclinico.com.br//public_html/" local="133647598916573381" remote="133722664200000000" Dst="0" />
<file name="app-kanban.css" server="ftp.appcasoclinico.com.br//public_html/" local="133647598929231223" remote="133722664200000000" Dst="0" />
<file name="app-todo.css" server="ftp.appcasoclinico.com.br//public_html/" local="133647598801411367" remote="133722664200000000" Dst="0" />
<file name="app-kanban.min.css" server="ftp.appcasoclinico.com.br//public_html/" local="133647598681748249" remote="133722664200000000" Dst="0" />
<file name="app-todo.min.css" server="ftp.appcasoclinico.com.br//public_html/" local="133647598783221756" remote="133722664200000000" Dst="0" />
<file name="authentication.css" server="ftp.appcasoclinico.com.br//public_html/" local="133647598709012874" remote="133722664200000000" Dst="0" />
<file name="authentication.min.css" server="ftp.appcasoclinico.com.br//public_html/" local="133647598665009284" remote="133722664200000000" Dst="0" />
<file name="dashboard-ecommerce.css" server="ftp.appcasoclinico.com.br//public_html/" local="133647598741843926" remote="133722664200000000" Dst="0" />
<file name="dashboard-ecommerce.min.css" server="ftp.appcasoclinico.com.br//public_html/" local="133647598832613069" remote="133722664200000000" Dst="0" />
<file name="modal-create-app.css" server="ftp.appcasoclinico.com.br//public_html/" local="133647598952873815" remote="133722664200000000" Dst="0" />
<file name="modal-create-app.min.css" server="ftp.appcasoclinico.com.br//public_html/" local="133647598859212463" remote="133722664200000000" Dst="0" />
<file name="page-blog.css" server="ftp.appcasoclinico.com.br//public_html/" local="133647598697757072" remote="133722664200000000" Dst="0" />
<file name="page-blog.min.css" server="ftp.appcasoclinico.com.br//public_html/" local="133647598818532590" remote="133722664200000000" Dst="0" />
<file name="page-coming-soon.css" server="ftp.appcasoclinico.com.br//public_html/" local="133647598652674229" remote="133722664200000000" Dst="0" />
<file name="page-coming-soon.min.css" server="ftp.appcasoclinico.com.br//public_html/" local="133647598865741500" remote="133722664200000000" Dst="0" />
<file name="page-faq.css" server="ftp.appcasoclinico.com.br//public_html/" local="133647598789704301" remote="133722664200000000" Dst="0" />
<file name="page-faq.min.css" server="ftp.appcasoclinico.com.br//public_html/" local="133647598878671418" remote="133722664200000000" Dst="0" />
<file name="page-knowledge-base.css" server="ftp.appcasoclinico.com.br//public_html/" local="133647598777405904" remote="133722664200000000" Dst="0" />
<file name="page-misc.css" server="ftp.appcasoclinico.com.br//public_html/" local="133647598838077673" remote="133722664200000000" Dst="0" />
<file name="page-knowledge-base.min.css" server="ftp.appcasoclinico.com.br//public_html/" local="133647598670807388" remote="133722664200000000" Dst="0" />
<file name="page-misc.min.css" server="ftp.appcasoclinico.com.br//public_html/" local="133647598897813657" remote="133722664200000000" Dst="0" />
<file name="page-pricing.css" server="ftp.appcasoclinico.com.br//public_html/" local="133647598658202403" remote="133722664200000000" Dst="0" />
<file name="page-pricing.min.css" server="ftp.appcasoclinico.com.br//public_html/" local="133647598961813554" remote="133722664200000000" Dst="0" />
<file name="page-profile.css" server="ftp.appcasoclinico.com.br//public_html/" local="133647598645912307" remote="133722664200000000" Dst="0" />
<file name="ui-feather.css" server="ftp.appcasoclinico.com.br//public_html/" local="133647598764538240" remote="133722664200000000" Dst="0" />
<file name="page-profile.min.css" server="ftp.appcasoclinico.com.br//public_html/" local="133647598751898733" remote="133722664200000000" Dst="0" />
<file name="ui-feather.min.css" server="ftp.appcasoclinico.com.br//public_html/" local="133647598825622381" remote="133722664200000000" Dst="0" />
</dwsync>